ezmapper/__init__.py
ezmapper/mapper.py
ezmapper/utils/__init__.py
ezmapper/utils/dates.py
ezmapper/utils/excel_formatting.py
ezmapper-0.0.2.dist-info/LICENSE
ezmapper-0.0.2.dist-info/METADATA
ezmapper-0.0.2.dist-info/WHEEL
ezmapper-0.0.2.dist-info/top_level.txt
ezmapper-0.0.2.dist-info/RECORD
