Metadata-Version: 2.1
Name: ezmapper
Version: 0.0.2
Summary: TBD
Author-email: Daniel <dakixr@gmail.com>
License-File: LICENSE
Requires-Dist: pandas
Requires-Dist: openpyxl
Requires-Dist: pyyaml
Requires-Dist: numpy
